README.md
setup.cfg
setup.py
dsbootcamp1/__init__.py
dsbootcamp1/hi.py
dsbootcamp1.egg-info/PKG-INFO
dsbootcamp1.egg-info/SOURCES.txt
dsbootcamp1.egg-info/dependency_links.txt
dsbootcamp1.egg-info/top_level.txt
dsbootcamp1/data_prep/__init__.py
dsbootcamp1/data_prep/data_prep.py
dsbootcamp1/eda/__init__.py
dsbootcamp1/eda/eda.py