Metadata-Version: 1.1
Name: dsbootcamp1
Version: 0.0.2
Summary: Data Science Tools
Home-page: https://github.com/merveasil/dsmlbc5
Author: Merve Asil
Author-email: UNKNOWN
License: MIT
Keywords: data science,machine learning,bootcamp
Platform: UNKNOWN
Classifier: Development Status :: 4 - Beta
Classifier: License :: OSI Approved :: MIT License
Classifier: Programming Language :: Python
Classifier: Programming Language :: Python :: 2.7
Classifier: Programming Language :: Python :: 3.5
Classifier: Topic :: Scientific/Engineering
